acutracer/__init__.py
acutracer/exporters/__init__.py
acutracer/exporters/jaeger_exporter.py
acutracer/instrumentors/python/langchain/__init__.py
acutracer/instrumentors/python/langchain/_tracer.py
acutracer/instrumentors/python/langchain/httpx_instrumentor.py
acutracer/instrumentors/python/langchain/instrumentor.py
acutracer/instrumentors/python/langchain/package.py
acutracer/instrumentors/python/langchain/py.typed
acutracer/instrumentors/python/langchain/requests_instrumentor.py
acutracer/instrumentors/python/langchain/version.py
acutracer/instrumentors/python/webapi/__init__.py
acutracer/instrumentors/python/webapi/instrumentor.py
acutracer-0.1.29.dist-info/METADATA
acutracer-0.1.29.dist-info/WHEEL
acutracer-0.1.29.dist-info/top_level.txt
acutracer-0.1.29.dist-info/RECORD
