Metadata-Version: 2.1
Name: acutracer
Version: 0.1.29
Summary: A Acuvity tracer that instruments the http calls
Author-email: Abhijit Herekar <abhijit@acuvity.ai>
Project-URL: Homepage, https://github.com/acuvity/acutracer
Project-URL: Bug Tracker, https://github.com/acuvity/acutracer/issues
Classifier: Programming Language :: Python :: 3
Classifier: Operating System :: OS Independent
Requires-Python: >=3.7
Requires-Dist: aiohappyeyeballs ==2.4.0
Requires-Dist: aiohttp
Requires-Dist: aiosignal
Requires-Dist: annotated-types
Requires-Dist: anyio
Requires-Dist: asgiref
Requires-Dist: attrs
Requires-Dist: certifi
Requires-Dist: charset-normalizer
Requires-Dist: click
Requires-Dist: Deprecated
Requires-Dist: distro
Requires-Dist: fastapi
Requires-Dist: frozenlist
Requires-Dist: googleapis-common-protos
Requires-Dist: grpcio
Requires-Dist: h11
Requires-Dist: httpcore
Requires-Dist: httpx
Requires-Dist: idna
Requires-Dist: importlib-metadata
Requires-Dist: jiter
Requires-Dist: jsonpatch
Requires-Dist: jsonpointer
Requires-Dist: langchain
Requires-Dist: langchain-core
Requires-Dist: langchain-openai
Requires-Dist: langchain-text-splitters
Requires-Dist: langsmith
Requires-Dist: loguru
Requires-Dist: multidict
Requires-Dist: numpy
Requires-Dist: openai
Requires-Dist: openinference-instrumentation ==0.1.15
Requires-Dist: openinference-instrumentation-openai ==0.1.14
Requires-Dist: openinference-semantic-conventions ==0.1.10
Requires-Dist: opentelemetry-api
Requires-Dist: opentelemetry-exporter-jaeger
Requires-Dist: opentelemetry-exporter-jaeger-proto-grpc
Requires-Dist: opentelemetry-exporter-jaeger-thrift
Requires-Dist: opentelemetry-instrumentation ==0.48b0
Requires-Dist: opentelemetry-instrumentation-asgi ==0.48b0
Requires-Dist: opentelemetry-instrumentation-fastapi ==0.48b0
Requires-Dist: opentelemetry-instrumentation-flask
Requires-Dist: opentelemetry-instrumentation-django
Requires-Dist: opentelemetry-sdk
Requires-Dist: opentelemetry-semantic-conventions ==0.48b0
Requires-Dist: opentelemetry-util-http ==0.48b0
Requires-Dist: opentelemetry-instrumentation-threading ==0.48b0
Requires-Dist: orjson
Requires-Dist: packaging
Requires-Dist: protobuf
Requires-Dist: pydantic
Requires-Dist: pydantic-core
Requires-Dist: PyYAML
Requires-Dist: regex
Requires-Dist: requests
Requires-Dist: setuptools
Requires-Dist: six
Requires-Dist: sniffio
Requires-Dist: SQLAlchemy
Requires-Dist: starlette
Requires-Dist: tenacity
Requires-Dist: thrift
Requires-Dist: tiktoken
Requires-Dist: tqdm
Requires-Dist: typing-extensions
Requires-Dist: urllib3
Requires-Dist: uvicorn
Requires-Dist: wheel
Requires-Dist: wrapt
Requires-Dist: yarl
Requires-Dist: zipp
Requires-Dist: Flask
Requires-Dist: django
